ICEstick/USB3300_parser_V1/modules/delay.v
/*
 * MIT License
 *
 * Copyright (c) 2018 Mario Rubio
 *
 * Permission is hereby granted, free of charge, to any person obtaining a copy
 * of this software and associated documentation files (the 'Software'), to deal
 * in the Software without restriction, including without limitation the rights
 * to use, copy, modify, merge, publish, distribute, sublicense, and/or sell
 * copies of the Software, and to permit persons to whom the Software is
 * furnished to do so, subject to the following conditions:
 *
 * The above copyright notice and this permission notice shall be included in all
 * copies or substantial portions of the Software.
 *
 * THE SOFTWARE IS PROVIDED 'AS IS', WITHOUT WARRANTY OF ANY KIND, EXPRESS OR
 * IMPLIED, INCLUDING BUT NOT LIMITED TO THE WARRANTIES OF MERCHANTABILITY,
 * FITNESS FOR A PARTICULAR PURPOSE AND NONINFRINGEMENT. IN NO EVENT SHALL THE
 * AUTHORS OR COPYRIGHT HOLDERS BE LIABLE FOR ANY CLAIM, DAMAGES OR OTHER
 * LIABILITY, WHETHER IN AN ACTION OF CONTRACT, TORT OR OTHERWISE, ARISING FROM,
 * OUT OF OR IN CONNECTION WITH THE SOFTWARE OR THE USE OR OTHER DEALINGS IN THE
 * SOFTWARE.
 */

/*
 * Revision History:
 *     Initial: 2018/05/27      Mario Rubio
 */

module delay #(parameter DELAY_VAL = 2)
              (input  wire clk,
               input  wire sig_in,
               output wire sig_out);

    //
    reg [DELAY_VAL-1+1:0]buffer = {DELAY_VAL+1{1'b0}};
    always @(posedge clk) begin
        buffer <= {sig_in, buffer[DELAY_VAL-1+1:1]};
    end
    assign sig_out = buffer[0];

endmodule

ICEstick/USB3300_parser_V1/modules/delay_tb.v
/*
 * MIT License
 *
 * Copyright (c) 2018 Mario Rubio
 *
 * Permission is hereby granted, free of charge, to any person obtaining a copy
 * of this software and associated documentation files (the 'Software'), to deal
 * in the Software without restriction, including without limitation the rights
 * to use, copy, modify, merge, publish, distribute, sublicense, and/or sell
 * copies of the Software, and to permit persons to whom the Software is
 * furnished to do so, subject to the following conditions:
 *
 * The above copyright notice and this permission notice shall be included in all
 * copies or substantial portions of the Software.
 *
 * THE SOFTWARE IS PROVIDED 'AS IS', WITHOUT WARRANTY OF ANY KIND, EXPRESS OR
 * IMPLIED, INCLUDING BUT NOT LIMITED TO THE WARRANTIES OF MERCHANTABILITY,
 * FITNESS FOR A PARTICULAR PURPOSE AND NONINFRINGEMENT. IN NO EVENT SHALL THE
 * AUTHORS OR COPYRIGHT HOLDERS BE LIABLE FOR ANY CLAIM, DAMAGES OR OTHER
 * LIABILITY, WHETHER IN AN ACTION OF CONTRACT, TORT OR OTHERWISE, ARISING FROM,
 * OUT OF OR IN CONNECTION WITH THE SOFTWARE OR THE USE OR OTHER DEALINGS IN THE
 * SOFTWARE.
 */

/*
 * Revision History:
 *     Initial: 2018/05/27      Mario Rubio
 */

module delay_tb();

    reg  d_in = 1'b0;
    reg  clk  = 1'b1;
    wire d_out;
    delay del (clk, d_in, d_out);

    // Clock
    always #1 clk = ~clk;

    initial begin
        $dumpfile("delay_tb.vcd");
        $dumpvars(0, delay_tb);

        #2 d_in = 1;
        #4 d_in = 0;
        #2 d_in = 1;
        #2 d_in = 0;
        #2 d_in = 1;
        #2 d_in = 0;
        #2 d_in = 1;
        #4 d_in = 0;
        #4 d_in = 1;

        #100 $finish;
    end

endmodule

ICEstick/USB3300_parser_V2/modules/delay/sim/delay_tb.vcd
$date
	Mon May 28 21:42:56 2018
$end
$version
	Icarus Verilog
$end
$timescale
	1s
$end
$scope module delay_tb $end
$var wire 1 ! d_out $end
$var reg 1 " clk $end
$var reg 1 # d_in $end
$scope module del $end
$var wire 1 " clk $end
$var wire 1 # sig_in $end
$var wire 1 ! sig_out $end
$var reg 3 $ buffer [2:0] $end
$upscope $end
$upscope $end
$enddefinitions $end
#0
$dumpvars
b0 $
0#
1"
0!
$end
#1
0"
#2
b100 $
1"
1#
#3
0"
#4
b110 $
1"
#5
0"
#6
1!
b11 $
1"
0#
#7
0"
#8
b101 $
1"
1#
#9
0"
#10
0!
b10 $
1"
0#
#11
0"
#12
1!
b101 $
1"
1#
#13
0"
#14
0!
b10 $
1"
0#
#15
0"
#16
1!
b101 $
1"
1#
#17
0"
#18
0!
b110 $
1"
#19
0"
#20
1!
b11 $
1"
0#
#21
0"
#22
b1 $
1"
#23
0"
#24
0!
b100 $
1"
1#
#25
0"
#26
b110 $
1"
#27
0"
#28
1!
b111 $
1"
