ICEstick/USB3300_sniffer/modules/ULPI/rtl/ULPI_REG_WRITE.v
/*
 * MIT License
 *
 * Copyright (c) 2018 Mario Rubio
 *
 MIT License

Copyright (c) 2015-present, Facebook, Inc.

Permission is hereby granted, free of charge, to any person obtaining a copy
of this software and associated documentation files (the "Software"), to deal
in the Software without restriction, including without limitation the rights
to use, copy, modify, merge, publish, distribute, sublicense, and/or sell
copies of the Software, and to permit persons to whom the Software is
furnished to do so, subject to the following conditions:

The above copyright notice and this permission notice shall be included in all
copies or substantial portions of the Software.

THE SOFTWARE IS PROVIDED "AS IS", WITHOUT WARRANTY OF ANY KIND, EXPRESS OR
IMPLIED, INCLUDING BUT NOT LIMITED TO THE WARRANTIES OF MERCHANTABILITY,
FITNESS FOR A PARTICULAR PURPOSE AND NONINFRINGEMENT. IN NO EVENT SHALL THE
AUTHORS OR COPYRIGHT HOLDERS BE LIABLE FOR ANY CLAIM, DAMAGES OR OTHER
LIABILITY, WHETHER IN AN ACTION OF CONTRACT, TORT OR OTHERWISE, ARISING FROM,
OUT OF OR IN CONNECTION WITH THE SOFTWARE OR THE USE OR OTHER DEALINGS IN THE
SOFTWARE.
 
 */

/*
 * Revision History:
 *     Initial:        2018/07/04        Mario Rubio
 */

/*
 This module has the instructions set that let write data into the PHY registers

 States:
    1. WRITE_IDLE. The module is doing nothing until the WRITE_DATA input is activated.
    2. WRITE_TXCMD. Once the write signal is asserted, the LINK has the ownership of the bus and send the TXCMD 8bit data ('10'cmd+{6bit Address}).
                    The PHY will respond activating the NXT signal indicating that TXCMD has been successfully latched.
    3. WRITE_SEND_DATA. Link drives the DATA to be stored in the register.
                        The PHY drives NXT high indicating that the data has been latched.
    4. WRITE_STP. Finally, the LINK drives HIGH STP, ending the writing of the register.

 */

`default_nettype none

module ULPI_REG_WRITE (
                      // System signals
                      input  wire clk, // Clock input signal
                      input  wire rst, // Master reset signal
                      // ULPI controller signals
                      input  wire WRITE_DATA, // Signal to initiate a register write
                      input  wire [7:0]DATA,  // Input that transmit the 8 bit DATA to be written in the ULPI register
                      input  wire [5:0]ADDR,  // Input that transmit the 6 bit address where we want to write the DATA
                      output wire BUSY,       // Output signal activated whenever is a Write operationn in progress
                      // ULPI pins
                      input  wire NXT,
                      output wire STP,
                      output wire [7:0]ULPI_DATA
                      );

    // CMD used to perform a register write 10xxxxxx
    parameter [1:0]REG_WRITE_CMD = 2'b10;

    /// ULPI_REG_WRITE Regs and wires
    // Outputs
    reg STP_r = 1'b0; assign STP = STP_r;

    // Inputs
    // #NONE

    // Buffers
    reg [7:0]DATA_buf_r = 8'b0;      // Buffer for the ULPI controller DATA input
    reg [7:0]ULPI_DATA_buf_r = 8'b0; // Buffer for the ULPI pins DATA output

    // Control registers
    reg [1:0]WRITE_state_r = 2'b0;   // Register to store the current state of the ULPI_REG_WRITE module

    // Flags
    wire WRITE_s_IDLE;      // 1 if WRITE_state_r == WRITE_IDLE, else 0
    wire WRITE_s_TXCMD;     // 1 if WRITE_state_r == WRITE_TXCMD, else 0
    wire WRITE_s_SEND_DATA; // 1 if WRITE_state_r == WRITE_SEND_DATA, else 0
    wire WRITE_s_STP;       // 1 if WRITE_state_r == WRITE_STP, else 0
    
    // Assigns
    assign WRITE_s_IDLE      = (WRITE_state_r == WRITE_IDLE)      ? 1'b1 : 1'b0; // #FLAG
    assign WRITE_s_TXCMD     = (WRITE_state_r == WRITE_TXCMD)     ? 1'b1 : 1'b0; // #FLAG
    assign WRITE_s_SEND_DATA = (WRITE_state_r == WRITE_SEND_DATA) ? 1'b1 : 1'b0; // #FLAG
    assign WRITE_s_STP       = (WRITE_state_r == WRITE_STP)       ? 1'b1 : 1'b0; // #FLAG
    assign BUSY              = !WRITE_s_IDLE;   // #OUTPUT
    assign ULPI_DATA         = ULPI_DATA_buf_r; // #OUTPUT
    /// End of ULPI_REG_WRITE Regs and wires

    /// ULPI_REG_WRITE States (See module description at the beginning to get more info)
    localparam WRITE_IDLE      = 2'b00;
    localparam WRITE_TXCMD     = 2'b01;
    localparam WRITE_SEND_DATA = 2'b10;
    localparam WRITE_STP       = 2'b11;
    /// End of ULPI_REG_WRITE States

    /// ULPI_REG_WRITE controller
    // States and actions
    // #FIGURE_NUMBER WRITE_state_machine
    always @(posedge clk) begin
        if(rst == 1'b1) begin
            // When a reset occurs, the default state is loaded, and the registers are purged
            WRITE_state_r <= WRITE_IDLE;
            STP_r <= 1'b0;
            ULPI_DATA_buf_r <= 8'b0;
        end
        else begin
            case(WRITE_state_r)
                WRITE_IDLE: begin
                    STP_r <= 1'b0;
                    // The state change once the Write signal (WRITE_DATA) is activated, elsewise, we do nothing
                    if(WRITE_DATA == 1'b1) begin
                        WRITE_state_r <= WRITE_TXCMD;

                        // The value of the DATA input may vary during the write process, so we store its initial value
                        DATA_buf_r      <= DATA;
                        ULPI_DATA_buf_r <= {REG_WRITE_CMD, ADDR};
                    end
                    else begin
                        WRITE_state_r <= WRITE_IDLE;
                        ULPI_DATA_buf_r <= 8'b0; // Default DATA output
                    end
                end
                WRITE_TXCMD: begin                   
                    // We wait until the PHY assert the NXT signal
                    if(NXT == 1'b1) begin
                        WRITE_state_r <= WRITE_SEND_DATA;

                        // Once TXCMD has been accepted, we send the new register value
                        ULPI_DATA_buf_r <= DATA_buf_r;
                    end
                    else WRITE_state_r <= WRITE_TXCMD;
                end
                WRITE_SEND_DATA: begin
                    // We wait again for an activated NXT signal
                    if(NXT == 1'b1) begin
                        WRITE_state_r <= WRITE_STP;
                    
                        // The STP signal is activated, ending the register write
                        STP_r <= 1'b1;
                        ULPI_DATA_buf_r <= 8'b0;
                    end
                    else WRITE_state_r <= WRITE_SEND_DATA;
                end
                WRITE_STP: begin
                    // The WRITE routine is done, so we go back to the IDLE state
                    WRITE_state_r <= WRITE_IDLE;
                    
                    // The STP pin is changed to a LOW level and the DATA output return to the initial state
                    STP_r <= 1'b0;
                    ULPI_DATA_buf_r <= 8'b0;
                end
                default: begin
                    // Just in case a not possible state value occurs, we go back to the inital state
                    WRITE_state_r <= WRITE_IDLE;
                    ULPI_DATA_buf_r <= 8'b0;
                    STP_r <= 1'b0;
                end
            endcase
        end
    end
    /// End of ULPI_REG_WRITE controller

endmodule

ICEstick/USB3300_sniffer/modules/ULPI/tb/ULPI_REG_WRITE_tb.v
/*
 * MIT License
 *
 * Copyright (c) 2018 Mario Rubio
 *
 MIT License

Copyright (c) 2015-present, Facebook, Inc.

Permission is hereby granted, free of charge, to any person obtaining a copy
of this software and associated documentation files (the "Software"), to deal
in the Software without restriction, including without limitation the rights
to use, copy, modify, merge, publish, distribute, sublicense, and/or sell
copies of the Software, and to permit persons to whom the Software is
furnished to do so, subject to the following conditions:

The above copyright notice and this permission notice shall be included in all
copies or substantial portions of the Software.

THE SOFTWARE IS PROVIDED "AS IS", WITHOUT WARRANTY OF ANY KIND, EXPRESS OR
IMPLIED, INCLUDING BUT NOT LIMITED TO THE WARRANTIES OF MERCHANTABILITY,
FITNESS FOR A PARTICULAR PURPOSE AND NONINFRINGEMENT. IN NO EVENT SHALL THE
AUTHORS OR COPYRIGHT HOLDERS BE LIABLE FOR ANY CLAIM, DAMAGES OR OTHER
LIABILITY, WHETHER IN AN ACTION OF CONTRACT, TORT OR OTHERWISE, ARISING FROM,
OUT OF OR IN CONNECTION WITH THE SOFTWARE OR THE USE OR OTHER DEALINGS IN THE
SOFTWARE.
 
 */

/*
 * Revision History:
 *     Initial:        2018/07/11        Mario Rubio
 */

module ULPI_REG_WRITE_tb ();

    // Registers and wires
    reg clk = 1'b0;
    reg rst = 1'b0;
    reg WD  = 1'b0;
    reg NXT = 1'b0;
    reg [7:0]DATA = 8'b0;
    reg [5:0]ADDR = 6'b0;

    wire [7:0]ULPI_DATA;
    wire STP;
    wire busy;

    // Module init
    ULPI_REG_WRITE WRITE_tb (clk, rst, WD, DATA, ADDR, busy, NXT, STP, ULPI_DATA);

    // CLK gen
    always #1 clk <= ~clk;

    // Simulation
    initial begin
      
        $dumpfile("sim/ULPI_REG_WRITE_tb.vcd");
        $dumpvars(0, ULPI_REG_WRITE_tb);

        #1 ADDR = 6'h1A; DATA = 8'h3A;

        #1 WD = 1;
        #2 WD = 0;

        #2 NXT = 1;
        #4 NXT = 0;
        
        #100 $finish;
    end

endmodule

ICEstick/USB3300_sniffer/modules/ULPI/sim/ULPI_REG_WRITE_tb.vcd
$date
	Thu Jul 12 13:22:34 2018
$end
$version
	Icarus Verilog
$end
$timescale
	1s
$end
$scope module ULPI_REG_WRITE_tb $end
$var wire 1 ! busy $end
$var wire 8 " ULPI_DATA [7:0] $end
$var wire 1 # STP $end
$var reg 6 $ ADDR [5:0] $end
$var reg 8 % DATA [7:0] $end
$var reg 1 & NXT $end
$var reg 1 ' WD $end
$var reg 1 ( clk $end
$var reg 1 ) rst $end
$scope module WRITE_tb $end
$var wire 6 * ADDR [5:0] $end
$var wire 8 + DATA [7:0] $end
$var wire 1 & NXT $end
$var wire 1 # STP $end
$var wire 8 , ULPI_DATA [7:0] $end
$var wire 1 ' WRITE_DATA $end
$var wire 1 ( clk $end
$var wire 1 ) rst $end
$var wire 1 - WRITE_s_TXCMD $end
$var wire 1 . WRITE_s_STP $end
$var wire 1 / WRITE_s_SEND_DATA $end
$var wire 1 0 WRITE_s_IDLE $end
$var wire 1 ! BUSY $end
$var reg 8 1 DATA_buf_r [7:0] $end
$var reg 1 2 STP_r $end
$var reg 8 3 ULPI_DATA_buf_r [7:0] $end
$var reg 2 4 WRITE_state_r [1:0] $end
$upscope $end
$upscope $end
$enddefinitions $end
#0
$dumpvars
b0 4
b0 3
02
b0 1
10
0/
0.
0-
b0 ,
b0 +
b0 *
0)
0(
0'
0&
b0 %
b0 $
0#
b0 "
0!
$end
#1
1(
b111010 %
b111010 +
b11010 $
b11010 *
#2
0(
1'
#3
1!
00
1-
b10011010 "
b10011010 ,
b10011010 3
b111010 1
b1 4
1(
#4
0(
0'
#5
1(
#6
0(
1&
#7
0-
1/
b111010 "
b111010 ,
b111010 3
b10 4
1(
#8
0(
#9
0/
1.
b0 "
b0 ,
b0 3
1#
12
b11 4
1(
#10
0(
0&
#11
0!
10
0.
0#
02
b0 4
1(
