ICEstick/USB3300_parser_V1/modules/clk_gen.v
/*
 * MIT License
 *
 * Copyright (c) 2018 Mario Rubio
 *
 * Permission is hereby granted, free of charge, to any person obtaining a copy
 * of this software and associated documentation files (the 'Software'), to deal
 * in the Software without restriction, including without limitation the rights
 * to use, copy, modify, merge, publish, distribute, sublicense, and/or sell
 * copies of the Software, and to permit persons to whom the Software is
 * furnished to do so, subject to the following conditions:
 *
 * The above copyright notice and this permission notice shall be included in all
 * copies or substantial portions of the Software.
 *
 * THE SOFTWARE IS PROVIDED 'AS IS', WITHOUT WARRANTY OF ANY KIND, EXPRESS OR
 * IMPLIED, INCLUDING BUT NOT LIMITED TO THE WARRANTIES OF MERCHANTABILITY,
 * FITNESS FOR A PARTICULAR PURPOSE AND NONINFRINGEMENT. IN NO EVENT SHALL THE
 * AUTHORS OR COPYRIGHT HOLDERS BE LIABLE FOR ANY CLAIM, DAMAGES OR OTHER
 * LIABILITY, WHETHER IN AN ACTION OF CONTRACT, TORT OR OTHERWISE, ARISING FROM,
 * OUT OF OR IN CONNECTION WITH THE SOFTWARE OR THE USE OR OTHER DEALINGS IN THE
 * SOFTWARE.
 */

/*
 * Revision History:
 *     Initial: 2018/05/17      Mario Rubio
 */

module clk_gen #(parameter DIVIDER = 9)
                (input  wire clk,
                 input  wire enable,
                 output wire new_clk,
                 output wire clk_pulse);

    // Main clock gen
    reg  [DIVIDER-1:0]new_clk_r = {DIVIDER{1'b0}};
    assign new_clk = new_clk_r[DIVIDER-1];
    always @(posedge clk) begin
        if(enable) begin
            new_clk_r <= new_clk_r + 1;
        end
        else begin
            new_clk_r <= {DIVIDER{1'b0}};
        end
    end

    // Pulse gen
    reg baud_last_r    = 1'b0;
    reg baud_posedge_r = 1'b0;
    always @(posedge clk) begin
        baud_posedge_r  <= !baud_last_r & new_clk;
    end
    always @(posedge clk) begin
        if(enable)
            baud_last_r <= new_clk;
    end

endmodule

ICEstick/USB3300_parser_V1/modules/UART.v
/*
 * MIT License
 *
 * Copyright (c) 2018 Mario Rubio
 *
 * Permission is hereby granted, free of charge, to any person obtaining a copy
 * of this software and associated documentation files (the 'Software'), to deal
 * in the Software without restriction, including without limitation the rights
 * to use, copy, modify, merge, publish, distribute, sublicense, and/or sell
 * copies of the Software, and to permit persons to whom the Software is
 * furnished to do so, subject to the following conditions:
 *
 * The above copyright notice and this permission notice shall be included in all
 * copies or substantial portions of the Software.
 *
 * THE SOFTWARE IS PROVIDED 'AS IS', WITHOUT WARRANTY OF ANY KIND, EXPRESS OR
 * IMPLIED, INCLUDING BUT NOT LIMITED TO THE WARRANTIES OF MERCHANTABILITY,
 * FITNESS FOR A PARTICULAR PURPOSE AND NONINFRINGEMENT. IN NO EVENT SHALL THE
 * AUTHORS OR COPYRIGHT HOLDERS BE LIABLE FOR ANY CLAIM, DAMAGES OR OTHER
 * LIABILITY, WHETHER IN AN ACTION OF CONTRACT, TORT OR OTHERWISE, ARISING FROM,
 * OUT OF OR IN CONNECTION WITH THE SOFTWARE OR THE USE OR OTHER DEALINGS IN THE
 * SOFTWARE.
 */

/*
 * Revision History:
 *     Initial: 2018/05/01      Mario Rubio
 */

/*
 * Ciertas partes de este código se basan en:
 * https://github.com/Obijuan/open-fpga-verilog-tutorial/wiki/Cap%C3%ADtulo-24%3A-Unidad-de-transmisi%C3%B3n-serie-as%C3%ADncrona
 */

`default_nettype none

// `include "clk_gen.v"

module UART #(parameter BAUD_DIVIDER = 9)
             (input  wire Rx,          // Rx input pin
              input  wire clk,         // reference clock input pin
              input  wire [7:0]I_DATA, // 8-bits data to send
              input  wire send_data,   // Send the current data in DATA IF there isn't any trasmission in progress
              output wire Tx,          // Tx output pin
              output wire TiP,         // Trasmission in Progress flag
              output wire NrD,         // New received Data flag
              output wire [7:0]O_DATA, // 8-bits data received
              output wire clk_baud     // Baudrate output
              );


    /// Baud clock gen
    wire baud_pulse;
    clk_gen #(.DIVIDER(BAUD_DIVIDER)) baud (clk, TiP, clk_baud, baud_pulse);
    /// End Baud clock gen

    /// Tx regs and wires
    // Outputs
    reg Tx_r  = 1'b1; assign Tx = Tx_r;
    
    // Inputs
    reg [7:0]I_DATA_r = 8'b0;
    reg send_data_r   = 1'b0;
    always @(posedge clk) begin
        send_data_r <= send_data;
    end
    always @(posedge clk) begin
        if((Tx_state_r == Tx_IDLE) && send_data == 1'b1)
            I_DATA_r <= I_DATA;
    end

    // Buffers
    reg [9:0]Tx_buf_r   = {10{1'b1}};

    // Control registers
    reg [3:0]Tx_ctrl_r  = 4'b0;
    reg [1:0]Tx_state_r = 2'b0;

    // Flags
    wire Tx_s_IDLE;
    wire Tx_s_TRANS;
    wire Tx_s_LOAD;
    wire Tx_s_WAIT;

    // Assigns
    assign Tx_s_IDLE  = (Tx_state_r == Tx_IDLE)  ? 1'b1 : 1'b0;
    assign Tx_s_LOAD  = (Tx_state_r == Tx_LOAD)  ? 1'b1 : 1'b0;
    assign Tx_s_TRANS = (Tx_state_r == Tx_TRANS) ? 1'b1 : 1'b0;
    assign Tx_s_WAIT  = (Tx_state_r == Tx_WAIT)  ? 1'b1 : 1'b0;
    assign TiP        = !Tx_s_IDLE;

    /// End of Tx regs and wires

    /// Tx States
    localparam Tx_IDLE   = 2'b00;
    localparam Tx_LOAD   = 2'b01;
    localparam Tx_TRANS  = 2'b10;
    localparam Tx_WAIT   = 2'b11;
    /// End of Tx States

    /// Tx controller
    always @(posedge clk) begin
        case (Tx_state_r)
            Tx_IDLE:  begin
                if(send_data_r == 1'b1) begin
                    Tx_state_r <= Tx_LOAD;
                end
                else begin
                    Tx_state_r <= Tx_IDLE;
                end
            end
            Tx_LOAD: begin
                Tx_state_r <= Tx_TRANS;
            end
            Tx_TRANS: begin
                if(clk_baud == 1'b1) begin
                    Tx_state_r <= Tx_WAIT;
                end
                else begin
                    Tx_state_r <= Tx_TRANS;
                end
            end 
            Tx_WAIT: begin
                if(Tx_ctrl_r == 4'b1011) begin
                    Tx_state_r <= Tx_IDLE;
                end
                else if(clk_baud == 1'b0) begin
                    Tx_state_r <= Tx_TRANS;
                end
                else begin
                    Tx_state_r <= Tx_WAIT;
                end
            end 
            default: begin
                Tx_state_r <= Tx_IDLE;
            end
        endcase
    end

    always @(posedge clk) begin
        Tx_r <= Tx_buf_r[0];
    end

    // Tx buffer
    always @(posedge clk) begin
        if(Tx_s_LOAD == 1'b1) begin
            Tx_buf_r <= {I_DATA_r, 2'b01};
        end
        else if(Tx_s_LOAD == 1'b0 && baud_pulse == 1'b1) begin
            Tx_buf_r <= {1'b1, Tx_buf_r[9:1]};
        end
    end

    // Tx transmission counter
    always @(posedge clk) begin
        if(Tx_s_LOAD == 1'b1) begin
            Tx_ctrl_r <= 4'b0;
        end
        else if(Tx_s_LOAD == 1'b0 && baud_pulse == 1'b1) begin
            Tx_ctrl_r <= Tx_ctrl_r + 1'b1;
        end
    end
    /// End of Tx controller


    /// Rx regs and wires
    /// End of Rx regs and wires
    
    /// Rx States
    /// End of Rx States

    /// Rx controller
    /// End of Rx controller
    
    /// Rx assigns
    assign NrD = 1'b0;
    /// End of Rx assigns

endmodule

ICEstick/USB3300_parser_V2/modules/UART/tb/UART_tb.v
/*
 * MIT License
 *
 * Copyright (c) 2018 Mario Rubio
 *
 * Permission is hereby granted, free of charge, to any person obtaining a copy
 * of this software and associated documentation files (the 'Software'), to deal
 * in the Software without restriction, including without limitation the rights
 * to use, copy, modify, merge, publish, distribute, sublicense, and/or sell
 * copies of the Software, and to permit persons to whom the Software is
 * furnished to do so, subject to the following conditions:
 *
 * The above copyright notice and this permission notice shall be included in all
 * copies or substantial portions of the Software.
 *
 * THE SOFTWARE IS PROVIDED 'AS IS', WITHOUT WARRANTY OF ANY KIND, EXPRESS OR
 * IMPLIED, INCLUDING BUT NOT LIMITED TO THE WARRANTIES OF MERCHANTABILITY,
 * FITNESS FOR A PARTICULAR PURPOSE AND NONINFRINGEMENT. IN NO EVENT SHALL THE
 * AUTHORS OR COPYRIGHT HOLDERS BE LIABLE FOR ANY CLAIM, DAMAGES OR OTHER
 * LIABILITY, WHETHER IN AN ACTION OF CONTRACT, TORT OR OTHERWISE, ARISING FROM,
 * OUT OF OR IN CONNECTION WITH THE SOFTWARE OR THE USE OR OTHER DEALINGS IN THE
 * SOFTWARE.
 */

/*
 * Revision History:
 *     Initial: 2018/05/01      Mario Rubio
 */

`include "../clk_gen/rtl/clk_gen.v"

module UART_tb();
   
    // Registers and wires
    reg  [7:0]data = 8'b0;
    reg  clk = 1'b0;
    reg  send_data = 1'b0;
    wire Tx;
    wire Rx;
    wire TiP;
    wire NrD;
    wire [7:0]O_DATA;

    wire ctrl;
    UART #(.BAUD_DIVIDER(1)) U1 (Rx, clk, data, send_data, Tx, TiP, NrD, O_DATA, ctrl);

    // Clock
    always #1 clk = ~clk;

    //
    initial begin
      
        $dumpfile("sim/UART_tb.vcd");
        $dumpvars(0, UART_tb);

        $monitor("data=%8b send_data=%1b Tx=%1b TiP=%1b",data, send_data, Tx, TiP);
        #2
        #2   data = 8'b01010101; send_data =1'b1;
        #2   send_data =1'b0;
        #100 $display("End!"); $finish;
    end

endmodule

ICEstick/USB3300_parser_V2/modules/UART/sim/UART_tb.vcd
$date
	Mon May 28 21:47:21 2018
$end
$version
	Icarus Verilog
$end
$timescale
	1s
$end
$scope module UART_tb $end
$var wire 1 ! NrD $end
$var wire 8 " O_DATA [7:0] $end
$var wire 1 # Rx $end
$var wire 1 $ ctrl $end
$var wire 1 % Tx $end
$var wire 1 & TiP $end
$var reg 1 ' clk $end
$var reg 8 ( data [7:0] $end
$var reg 1 ) send_data $end
$scope module U1 $end
$var wire 8 * I_DATA [7:0] $end
$var wire 1 ! NrD $end
$var wire 8 + O_DATA [7:0] $end
$var wire 1 # Rx $end
$var wire 1 % Tx $end
$var wire 1 ' clk $end
$var wire 1 ) send_data $end
$var wire 1 $ clk_baud $end
$var wire 1 , baud_pulse $end
$var wire 1 - Tx_s_WAIT $end
$var wire 1 . Tx_s_TRANS $end
$var wire 1 / Tx_s_LOAD $end
$var wire 1 0 Tx_s_IDLE $end
$var wire 1 & TiP $end
$var reg 8 1 I_DATA_r [7:0] $end
$var reg 10 2 Tx_buf_r [9:0] $end
$var reg 4 3 Tx_ctrl_r [3:0] $end
$var reg 1 4 Tx_r $end
$var reg 2 5 Tx_state_r [1:0] $end
$var reg 1 6 send_data_r $end
$scope module baud $end
$var wire 1 ' clk $end
$var wire 1 , clk_pulse $end
$var wire 1 7 enable $end
$var wire 1 $ new_clk $end
$var reg 1 8 baud_last_r $end
$var reg 1 9 baud_posedge_r $end
$var reg 1 : new_clk_r $end
$upscope $end
$upscope $end
$upscope $end
$enddefinitions $end
#0
$dumpvars
0:
09
08
17
06
b0 5
14
b0 3
b1111111111 2
b0 1
10
0/
0.
0-
0,
bz +
b0 *
0)
b0 (
0'
0&
1%
0$
z#
bz "
0!
$end
#1
1$
1:
1'
#2
0'
#3
0$
18
1,
19
0:
1'
#4
0'
1)
b1010101 (
b1010101 *
#5
1$
1:
0,
09
08
16
b1010101 1
b1 3
1'
#6
0'
0)
#7
1&
00
1/
0$
b1 5
06
18
1,
19
0:
1'
#8
0'
#9
1$
0/
1.
1:
0,
09
08
b10 5
b101010101 2
b0 3
1'
#10
0'
#11
0.
1-
0$
b11 5
18
1,
19
0:
1'
#12
0'
#13
1$
1.
0-
1:
0,
09
08
b10 5
b1010101010 2
b1 3
1'
#14
0'
#15
0.
1-
0$
0%
04
b11 5
18
1,
19
0:
1'
#16
0'
#17
1$
1.
0-
1:
0,
09
08
b10 5
b1101010101 2
b10 3
1'
#18
0'
#19
0.
1-
0$
1%
14
b11 5
18
1,
19
0:
1'
#20
0'
#21
1$
1.
0-
1:
0,
09
08
b10 5
b1110101010 2
b11 3
1'
#22
0'
#23
0.
1-
0$
0%
04
b11 5
18
1,
19
0:
1'
#24
0'
#25
1$
1.
0-
1:
0,
09
08
b10 5
b1111010101 2
b100 3
1'
#26
0'
#27
0.
1-
0$
1%
14
b11 5
18
1,
19
0:
1'
#28
0'
#29
1$
1.
0-
1:
0,
09
08
b10 5
b1111101010 2
b101 3
1'
#30
0'
#31
0.
1-
0$
0%
04
b11 5
18
1,
19
0:
1'
#32
0'
#33
1$
1.
0-
1:
0,
09
08
b10 5
b1111110101 2
b110 3
1'
#34
0'
#35
0.
1-
0$
1%
14
b11 5
18
1,
19
0:
1'
#36
0'
#37
1$
1.
0-
1:
0,
09
08
b10 5
b1111111010 2
b111 3
1'
#38
0'
#39
0.
1-
0$
0%
04
b11 5
18
1,
19
0:
1'
#40
0'
#41
1$
1.
0-
1:
0,
09
08
b10 5
b1111111101 2
b1000 3
1'
#42
0'
#43
0.
1-
0$
1%
14
b11 5
18
1,
19
0:
1'
#44
0'
#45
1$
1.
0-
1:
0,
09
08
b10 5
b1111111110 2
b1001 3
1'
#46
0'
#47
0.
1-
0$
0%
04
b11 5
18
1,
19
0:
1'
#48
0'
#49
1$
1.
0-
1:
0,
09
08
b10 5
b1111111111 2
b1010 3
1'
#50
0'
#51
0.
1-
0$
1%
14
b11 5
18
1,
19
0:
1'
#52
0'
#53
1$
1.
0-
1:
0,
09
08
b10 5
b1011 3
1'
#54
0'
#55
0.
1-
0$
b11 5
18
1,
19
0:
1'
#56
0'
#57
1$
0&
10
0-
1:
0,
09
08
b0 5
b1100 3
1'
#58
0'
#59
0$
18
1,
19
0:
1'
#60
0'
#61
1$
1:
0,
09
08
b1101 3
1'
#62
0'
#63
0$
18
1,
19
0:
1'
#64
0'
#65
1$
1:
0,
09
08
b1110 3
1'
#66
0'
#67
0$
18
1,
19
0:
1'
#68
0'
#69
1$
1:
0,
09
08
b1111 3
1'
#70
0'
#71
0$
18
1,
19
0:
1'
#72
0'
#73
1$
1:
0,
09
08
b0 3
1'
#74
0'
#75
0$
18
1,
19
0:
1'
#76
0'
#77
1$
1:
0,
09
08
b1 3
1'
#78
0'
#79
0$
18
1,
19
0:
1'
#80
0'
#81
1$
1:
0,
09
08
b10 3
1'
#82
0'
#83
0$
18
1,
19
0:
1'
#84
0'
#85
1$
1:
0,
09
08
b11 3
1'
#86
0'
#87
0$
18
1,
19
0:
1'
#88
0'
#89
1$
1:
0,
09
08
b100 3
1'
#90
0'
#91
0$
18
1,
19
0:
1'
#92
0'
#93
1$
1:
0,
09
08
b101 3
1'
#94
0'
#95
0$
18
1,
19
0:
1'
#96
0'
#97
1$
1:
0,
09
08
b110 3
1'
#98
0'
#99
0$
18
1,
19
0:
1'
#100
0'
#101
1$
1:
0,
09
08
b111 3
1'
#102
0'
#103
0$
18
1,
19
0:
1'
#104
0'
#105
1$
1:
0,
09
08
b1000 3
1'
