ICEstick/USB3300_parser_V1/modules/fifo_stack_u.v
/*
 * MIT License
 *
 * Copyright (c) 2018 Mario Rubio
 *
 * Permission is hereby granted, free of charge, to any person obtaining a copy
 * of this software and associated documentation files (the 'Software'), to deal
 * in the Software without restriction, including without limitation the rights
 * to use, copy, modify, merge, publish, distribute, sublicense, and/or sell
 * copies of the Software, and to permit persons to whom the Software is
 * furnished to do so, subject to the following conditions:
 *
 * The above copyright notice and this permission notice shall be included in all
 * copies or substantial portions of the Software.
 *
 * THE SOFTWARE IS PROVIDED 'AS IS', WITHOUT WARRANTY OF ANY KIND, EXPRESS OR
 * IMPLIED, INCLUDING BUT NOT LIMITED TO THE WARRANTIES OF MERCHANTABILITY,
 * FITNESS FOR A PARTICULAR PURPOSE AND NONINFRINGEMENT. IN NO EVENT SHALL THE
 * AUTHORS OR COPYRIGHT HOLDERS BE LIABLE FOR ANY CLAIM, DAMAGES OR OTHER
 * LIABILITY, WHETHER IN AN ACTION OF CONTRACT, TORT OR OTHERWISE, ARISING FROM,
 * OUT OF OR IN CONNECTION WITH THE SOFTWARE OR THE USE OR OTHER DEALINGS IN THE
 * SOFTWARE.
 */

/*
 * Revision History:
 *     Initial: 2018/05/22      Mario Rubio
 */

module fifo_stack_u #(parameter STACK_SIZE = 8)
                     (input  wire clk,       // Reference clock
                      input  wire i_data,    // New input data
                      input  wire save,      // Input to save the current bit in i_data
                      input  wire pop,       // Input to pop the first bit in the stack
                      input  wire reset,     // Input to reset the stack
                      output wire o_data,    // Output bit, always the first bit in the stack
                      output wire fifo_full, // Stack full flag
                      output wire fifo_empty,// Stack empty flag
                      output wire fifo_busy  // Module Busy, no new operation allowed
                      );

    localparam STACK_SIZE_N = $clog2(STACK_SIZE+1)/$clog2(2);

    /// FIFO regs and wires
    // Outputs
    reg o_data_r = 1'b0; assign o_data = o_data_r;

    // Inputs
    reg i_data_r = 1'b0;
    reg save_r   = 1'b0;
    reg pop_r    = 1'b0;
    reg reset_r  = 1'b0;
    always @(posedge clk) begin
        if(fifo_s_IDLE && save == 1'b1) begin
            i_data_r <= i_data;
        end
    end
    always @(posedge clk) begin
        save_r   <= save;
        pop_r    <= pop;
        reset_r  <= reset;
    end

    // Buffers
    reg [STACK_SIZE-1:0]memory = {STACK_SIZE{1'b0}};

    // Control registers
    reg [STACK_SIZE_N-1:0]fifo_position_r = {STACK_SIZE_N{1'b0}};
    reg [1:0]fifo_state_r = 2'b0;

    // Flags
    wire fifo_s_IDLE;
    wire fifo_s_SAVE;
    wire fifo_s_POP;
    wire fifo_s_RST;

    // Assigns
    assign fifo_s_IDLE = (fifo_state_r == FIFO_IDLE) ? 1'b1 : 1'b0;
    assign fifo_s_SAVE = (fifo_state_r == FIFO_SAVE) ? 1'b1 : 1'b0;
    assign fifo_s_POP  = (fifo_state_r == FIFO_POP)  ? 1'b1 : 1'b0;
    assign fifo_full   = (fifo_position_r == (STACK_SIZE+1)) ? 1'b1 : 1'b0;
    assign fifo_empty  = (fifo_position_r == 0) ? 1'b1 : 1'b0;
    assign fifo_busy   = !fifo_s_IDLE;

    /// End of FIFO regs and wires

    /// FIFO states
    localparam FIFO_IDLE = 2'b00; // Default state. Do nothing.
    localparam FIFO_SAVE = 2'b01; // Save a new value into the memory
    localparam FIFO_POP  = 2'b10; // Pop the first value of the memory
    localparam FIFO_WAIT = 2'b11; // Delay to show the new values in the output
    /// End of FIFO states

    /// FIFO controller
    always @(posedge clk) begin
        if(reset_r) begin
            fifo_state_r <= FIFO_IDLE;
            memory <= {STACK_SIZE{1'b0}};
            fifo_position_r <= {STACK_SIZE_N{1'b0}};
        end
        else begin
            case(fifo_state_r)
                FIFO_IDLE: begin
                    if(save_r && !pop_r)
                        fifo_state_r <= FIFO_SAVE;
                    else if(pop_r && !save_r)
                        fifo_state_r <= FIFO_POP;
                    else
                        fifo_state_r <= FIFO_IDLE;
                end
                FIFO_SAVE: begin
                    fifo_state_r <= FIFO_WAIT;
                end
                FIFO_POP: begin
                    fifo_state_r <= FIFO_WAIT;
                end
                FIFO_WAIT: begin
                    fifo_state_r <= FIFO_IDLE;
                end
                default: begin
                    fifo_state_r <= FIFO_IDLE;
                end
            endcase
        end
    end

    always @(posedge clk) begin
        o_data_r <= memory[0];
    end

    // Memory modify
    always @(posedge clk) begin
        if(fifo_s_IDLE == 1'b1) begin
        end
        else if(fifo_s_SAVE == 1'b1) begin
            if(fifo_full == 1'b0) begin
                memory[fifo_position_r] <= i_data_r;
            end
        end
        else if(fifo_s_POP == 1'b1) begin
            if(fifo_empty == 1'b0) begin
                memory <= memory>>1;
            end
        end
    end

    // fifo position change
    always @(posedge clk) begin
        if(fifo_s_IDLE == 1'b1) begin
        end
        else if(fifo_s_SAVE == 1'b1) begin
            if(fifo_full == 1'b0) begin
                fifo_position_r <= fifo_position_r + 1'b1;
            end
        end
        else if(fifo_s_POP == 1'b1) begin
            if(fifo_empty == 1'b0) begin
                fifo_position_r <= fifo_position_r - 1'b1;
            end
        end
    end
    /// End of FIFO controller

endmodule

ICEstick/USB3300_parser_V1/modules/fifo_stack.v
/*
 * MIT License
 *
 * Copyright (c) 2018 Mario Rubio
 *
 * Permission is hereby granted, free of charge, to any person obtaining a copy
 * of this software and associated documentation files (the 'Software'), to deal
 * in the Software without restriction, including without limitation the rights
 * to use, copy, modify, merge, publish, distribute, sublicense, and/or sell
 * copies of the Software, and to permit persons to whom the Software is
 * furnished to do so, subject to the following conditions:
 *
 * The above copyright notice and this permission notice shall be included in all
 * copies or substantial portions of the Software.
 *
 * THE SOFTWARE IS PROVIDED 'AS IS', WITHOUT WARRANTY OF ANY KIND, EXPRESS OR
 * IMPLIED, INCLUDING BUT NOT LIMITED TO THE WARRANTIES OF MERCHANTABILITY,
 * FITNESS FOR A PARTICULAR PURPOSE AND NONINFRINGEMENT. IN NO EVENT SHALL THE
 * AUTHORS OR COPYRIGHT HOLDERS BE LIABLE FOR ANY CLAIM, DAMAGES OR OTHER
 * LIABILITY, WHETHER IN AN ACTION OF CONTRACT, TORT OR OTHERWISE, ARISING FROM,
 * OUT OF OR IN CONNECTION WITH THE SOFTWARE OR THE USE OR OTHER DEALINGS IN THE
 * SOFTWARE.
 */

/*
 * Revision History:
 *     Initial: 2018/05/21      Mario Rubio
 */

`include "fifo_stack_u.v"

module fifo_stack #(parameter STACK_SIZE  = 15,
                    parameter STACK_WIDTH = 8)
                   (input  wire clk,                     // Master clock signal
                    input  wire [STACK_WIDTH-1:0]I_DATA, // Input data [STACK_WIDTH]
                    input  wire FIFO_save,               // Input to save the current data in I_DATA
                    input  wire FIFO_pop,                // Input to pop the first row in the stack
                    input  wire FIFO_reset,              // Input to reset the stack
                    output wire [STACK_WIDTH-1:0]O_DATA, // Output data, always the first row in the stack
                    output wire FIFO_full,               // Stack full flag
                    output wire FIFO_empty,              // Stack empty flag
                    output wire FIFO_busy                // Stack busy flag
                   );

    /// Registers and wires
    wire [STACK_WIDTH-1:0]full;
    wire [STACK_WIDTH-1:0]empty;
    wire [STACK_WIDTH-1:0]busy;
    /// End of Registers and wires

    /// Assigns
    assign FIFO_full  = (full  == {STACK_WIDTH{1'b0}}) ? 1'b0 : 1'b1; 
    assign FIFO_empty = (empty == {STACK_WIDTH{1'b0}}) ? 1'b0 : 1'b1; 
    assign FIFO_busy  = (busy  == {STACK_WIDTH{1'b0}}) ? 1'b0 : 1'b1; 
    /// End of Assigns

    /// Stack gen with STACK_SIZE sub 1-bit stacks
    genvar i;

    generate
        for(i=0; i<STACK_WIDTH; i=i+1) begin
           fifo_stack_u #(.STACK_SIZE(STACK_SIZE))
                subFIFO  (clk, I_DATA[i], FIFO_save,
                          FIFO_pop, FIFO_reset, O_DATA[i],
                          full[i], empty[i], busy[i]); 
        end
    endgenerate
    /// End of Stack gen with STACK_SIZE sub 1-bit stacks

endmodule

ICEstick/USB3300_parser_V1/modules/fifo_stack_tb.v
/*
 * MIT License
 *
 * Copyright (c) 2018 Mario Rubio
 *
 * Permission is hereby granted, free of charge, to any person obtaining a copy
 * of this software and associated documentation files (the 'Software'), to deal
 * in the Software without restriction, including without limitation the rights
 * to use, copy, modify, merge, publish, distribute, sublicense, and/or sell
 * copies of the Software, and to permit persons to whom the Software is
 * furnished to do so, subject to the following conditions:
 *
 * The above copyright notice and this permission notice shall be included in all
 * copies or substantial portions of the Software.
 *
 * THE SOFTWARE IS PROVIDED 'AS IS', WITHOUT WARRANTY OF ANY KIND, EXPRESS OR
 * IMPLIED, INCLUDING BUT NOT LIMITED TO THE WARRANTIES OF MERCHANTABILITY,
 * FITNESS FOR A PARTICULAR PURPOSE AND NONINFRINGEMENT. IN NO EVENT SHALL THE
 * AUTHORS OR COPYRIGHT HOLDERS BE LIABLE FOR ANY CLAIM, DAMAGES OR OTHER
 * LIABILITY, WHETHER IN AN ACTION OF CONTRACT, TORT OR OTHERWISE, ARISING FROM,
 * OUT OF OR IN CONNECTION WITH THE SOFTWARE OR THE USE OR OTHER DEALINGS IN THE
 * SOFTWARE.
 */

/*
 * Revision History:
 *     Initial: 2018/05/22      Mario Rubio
 */

module fifo_stack_tb();

    reg clk = 1'b0;
    reg [7:0]I_DATA = 1'b0;
    reg save = 1'b0;
    reg pop = 1'b0;
    wire reset; assign reset = 1'b0;
    wire [7:0]O_DATA;
    wire full;
    wire empty;
    wire busy;
    fifo_stack FIFO(clk, I_DATA, save, pop, reset, 
                        O_DATA, full, empty, busy);

    // Clock
    always #1 clk = ~clk;

    initial begin
        $dumpfile("fifo_stack.vcd");
        $dumpvars(0, fifo_stack_tb);

        // $monitor("Input: %1b  Output: %1b  Save: %1b  Pop: %1b  Full: %1b  Empty: %1b", I_DATA, O_DATA, save, pop, full, empty);
        
        $display("IN  . SAVE. OUT . EMPT.");
        #2 
        #2 save <= 0; pop <= 0;

           $display("Save 1 [%b]", "A");
           $display("I: %b. S: %b. O: %b. E: %b. [%b]", I_DATA, save, O_DATA, empty, busy);
        #2 I_DATA <= "A";

           $display("I: %b. S: %b. O: %b. E: %b. [%b]", I_DATA, save, O_DATA, empty, busy);
        #2 save <= 1;

        #2 $display("I: %b. S: %b. O: %b. E: %b. [%b]", I_DATA, save, O_DATA, empty, busy);
           save <= 0; I_DATA <= 0;

        #2 $display("I: %b. S: %b. O: %b. E: %b. [%b]", I_DATA, save, O_DATA, empty, busy);
        #2 $display("I: %b. S: %b. O: %b. E: %b. [%b]", I_DATA, save, O_DATA, empty, busy);
        #2 $display("I: %b. S: %b. O: %b. E: %b. [%b]", I_DATA, save, O_DATA, empty, busy);
        
           $display("Save 2 [%b]", "[");
        #2 I_DATA <= "["; save <= 1;
        
           $display("I: %b. S: %b. O: %b. E: %b. [%b]", I_DATA, save, O_DATA, empty, busy);
        #2 I_DATA <= 0; save <= 0;
           $display("I: %b. S: %b. O: %b. E: %b. [%b]", I_DATA, save, O_DATA, empty, busy);

        #2 $display("I: %b. S: %b. O: %b. E: %b. [%b]", I_DATA, save, O_DATA, empty, busy);
        #2 $display("I: %b. S: %b. O: %b. E: %b. [%b]", I_DATA, save, O_DATA, empty, busy);
        #2 $display("I: %b. S: %b. O: %b. E: %b. [%b]", I_DATA, save, O_DATA, empty, busy);
        
           $display("Save 3 [%b]", "c");
        #2 I_DATA <= "c"; save <= 1;
        
           $display("I: %b. S: %b. O: %b. E: %b. [%b]", I_DATA, save, O_DATA, empty, busy);
        #2 I_DATA <= 0; save <= 0;
           $display("I: %b. S: %b. O: %b. E: %b. [%b]", I_DATA, save, O_DATA, empty, busy);

        #2 $display("I: %b. S: %b. O: %b. E: %b. [%b]", I_DATA, save, O_DATA, empty, busy);
        #2 $display("I: %b. S: %b. O: %b. E: %b. [%b]", I_DATA, save, O_DATA, empty, busy);
        #2 $display("I: %b. S: %b. O: %b. E: %b. [%b]", I_DATA, save, O_DATA, empty, busy);

           $display("Pop 1");
        #2 pop <=1;
        
           $display("I: %b. S: %b. O: %b. E: %b. [%b]", I_DATA, save, O_DATA, empty, busy);
        #2 pop <= 0;

        #2 $display("I: %b. S: %b. O: %b. E: %b. [%b]", I_DATA, save, O_DATA, empty, busy);
        #2 $display("I: %b. S: %b. O: %b. E: %b. [%b]", I_DATA, save, O_DATA, empty, busy);
        #2 $display("I: %b. S: %b. O: %b. E: %b. [%b]", I_DATA, save, O_DATA, empty, busy);
        
           $display("Pop 2");
        #2 pop <=1;
        
           $display("I: %b. S: %b. O: %b. E: %b. [%b]", I_DATA, save, O_DATA, empty, busy);
        #2 pop <= 0;

        #2 $display("I: %b. S: %b. O: %b. E: %b. [%b]", I_DATA, save, O_DATA, empty, busy);
        #2 $display("I: %b. S: %b. O: %b. E: %b. [%b]", I_DATA, save, O_DATA, empty, busy);
        #2 $display("I: %b. S: %b. O: %b. E: %b. [%b]", I_DATA, save, O_DATA, empty, busy);
        
           $display("Pop 3");
        #2 pop <=1;
        
           $display("I: %b. S: %b. O: %b. E: %b. [%b]", I_DATA, save, O_DATA, empty, busy);
        #2 pop <= 0;

        #2 $display("I: %b. S: %b. O: %b. E: %b. [%b]", I_DATA, save, O_DATA, empty, busy);
        #2 $display("I: %b. S: %b. O: %b. E: %b. [%b]", I_DATA, save, O_DATA, empty, busy);
        #2 $display("I: %b. S: %b. O: %b. E: %b. [%b]", I_DATA, save, O_DATA, empty, busy);

        #64 $finish;
    end

endmodule

ICEstick/USB3300_parser_V1/modules/fifo_stack.vcd
$date
	Wed May 23 18:50:42 2018
$end
$version
	Icarus Verilog
$end
$timescale
	1s
$end
$scope module fifo_stack_tb $end
$var wire 1 ! reset $end
$var wire 1 " full $end
$var wire 1 # empty $end
$var wire 1 $ busy $end
$var wire 8 % O_DATA [7:0] $end
$var reg 8 & I_DATA [7:0] $end
$var reg 1 ' clk $end
$var reg 1 ( pop $end
$var reg 1 ) save $end
$scope module FIFO $end
$var wire 1 ( FIFO_pop $end
$var wire 1 ! FIFO_reset $end
$var wire 1 ) FIFO_save $end
$var wire 8 * I_DATA [7:0] $end
$var wire 1 ' clk $end
$var wire 8 + full [7:0] $end
$var wire 8 , empty [7:0] $end
$var wire 8 - busy [7:0] $end
$var wire 8 . O_DATA [7:0] $end
$var wire 1 " FIFO_full $end
$var wire 1 # FIFO_empty $end
$var wire 1 $ FIFO_busy $end
$scope begin genblk1[0] $end
$scope module subFIFO $end
$var wire 1 ' clk $end
$var wire 1 / i_data $end
$var wire 1 ( pop $end
$var wire 1 ! reset $end
$var wire 1 ) save $end
$var wire 1 0 o_data $end
$var wire 1 1 fifo_s_SAVE $end
$var wire 1 2 fifo_s_POP $end
$var wire 1 3 fifo_s_IDLE $end
$var wire 1 4 fifo_full $end
$var wire 1 5 fifo_empty $end
$var wire 1 6 fifo_busy $end
$var reg 4 7 fifo_position_r [3:0] $end
$var reg 2 8 fifo_state_r [1:0] $end
$var reg 1 9 i_data_r $end
$var reg 15 : memory [14:0] $end
$var reg 1 0 o_data_r $end
$var reg 1 ; pop_r $end
$var reg 1 < reset_r $end
$var reg 1 = save_r $end
$upscope $end
$upscope $end
$scope begin genblk1[1] $end
$scope module subFIFO $end
$var wire 1 ' clk $end
$var wire 1 > i_data $end
$var wire 1 ( pop $end
$var wire 1 ! reset $end
$var wire 1 ) save $end
$var wire 1 ? o_data $end
$var wire 1 @ fifo_s_SAVE $end
$var wire 1 A fifo_s_POP $end
$var wire 1 B fifo_s_IDLE $end
$var wire 1 C fifo_full $end
$var wire 1 D fifo_empty $end
$var wire 1 E fifo_busy $end
$var reg 4 F fifo_position_r [3:0] $end
$var reg 2 G fifo_state_r [1:0] $end
$var reg 1 H i_data_r $end
$var reg 15 I memory [14:0] $end
$var reg 1 ? o_data_r $end
$var reg 1 J pop_r $end
$var reg 1 K reset_r $end
$var reg 1 L save_r $end
$upscope $end
$upscope $end
$scope begin genblk1[2] $end
$scope module subFIFO $end
$var wire 1 ' clk $end
$var wire 1 M i_data $end
$var wire 1 ( pop $end
$var wire 1 ! reset $end
$var wire 1 ) save $end
$var wire 1 N o_data $end
$var wire 1 O fifo_s_SAVE $end
$var wire 1 P fifo_s_POP $end
$var wire 1 Q fifo_s_IDLE $end
$var wire 1 R fifo_full $end
$var wire 1 S fifo_empty $end
$var wire 1 T fifo_busy $end
$var reg 4 U fifo_position_r [3:0] $end
$var reg 2 V fifo_state_r [1:0] $end
$var reg 1 W i_data_r $end
$var reg 15 X memory [14:0] $end
$var reg 1 N o_data_r $end
$var reg 1 Y pop_r $end
$var reg 1 Z reset_r $end
$var reg 1 [ save_r $end
$upscope $end
$upscope $end
$scope begin genblk1[3] $end
$scope module subFIFO $end
$var wire 1 ' clk $end
$var wire 1 \ i_data $end
$var wire 1 ( pop $end
$var wire 1 ! reset $end
$var wire 1 ) save $end
$var wire 1 ] o_data $end
$var wire 1 ^ fifo_s_SAVE $end
$var wire 1 _ fifo_s_POP $end
$var wire 1 ` fifo_s_IDLE $end
$var wire 1 a fifo_full $end
$var wire 1 b fifo_empty $end
$var wire 1 c fifo_busy $end
$var reg 4 d fifo_position_r [3:0] $end
$var reg 2 e fifo_state_r [1:0] $end
$var reg 1 f i_data_r $end
$var reg 15 g memory [14:0] $end
$var reg 1 ] o_data_r $end
$var reg 1 h pop_r $end
$var reg 1 i reset_r $end
$var reg 1 j save_r $end
$upscope $end
$upscope $end
$scope begin genblk1[4] $end
$scope module subFIFO $end
$var wire 1 ' clk $end
$var wire 1 k i_data $end
$var wire 1 ( pop $end
$var wire 1 ! reset $end
$var wire 1 ) save $end
$var wire 1 l o_data $end
$var wire 1 m fifo_s_SAVE $end
$var wire 1 n fifo_s_POP $end
$var wire 1 o fifo_s_IDLE $end
$var wire 1 p fifo_full $end
$var wire 1 q fifo_empty $end
$var wire 1 r fifo_busy $end
$var reg 4 s fifo_position_r [3:0] $end
$var reg 2 t fifo_state_r [1:0] $end
$var reg 1 u i_data_r $end
$var reg 15 v memory [14:0] $end
$var reg 1 l o_data_r $end
$var reg 1 w pop_r $end
$var reg 1 x reset_r $end
$var reg 1 y save_r $end
$upscope $end
$upscope $end
$scope begin genblk1[5] $end
$scope module subFIFO $end
$var wire 1 ' clk $end
$var wire 1 z i_data $end
$var wire 1 ( pop $end
$var wire 1 ! reset $end
$var wire 1 ) save $end
$var wire 1 { o_data $end
$var wire 1 | fifo_s_SAVE $end
$var wire 1 } fifo_s_POP $end
$var wire 1 ~ fifo_s_IDLE $end
$var wire 1 !" fifo_full $end
$var wire 1 "" fifo_empty $end
$var wire 1 #" fifo_busy $end
$var reg 4 $" fifo_position_r [3:0] $end
$var reg 2 %" fifo_state_r [1:0] $end
$var reg 1 &" i_data_r $end
$var reg 15 '" memory [14:0] $end
$var reg 1 { o_data_r $end
$var reg 1 (" pop_r $end
$var reg 1 )" reset_r $end
$var reg 1 *" save_r $end
$upscope $end
$upscope $end
$scope begin genblk1[6] $end
$scope module subFIFO $end
$var wire 1 ' clk $end
$var wire 1 +" i_data $end
$var wire 1 ( pop $end
$var wire 1 ! reset $end
$var wire 1 ) save $end
$var wire 1 ," o_data $end
$var wire 1 -" fifo_s_SAVE $end
$var wire 1 ." fifo_s_POP $end
$var wire 1 /" fifo_s_IDLE $end
$var wire 1 0" fifo_full $end
$var wire 1 1" fifo_empty $end
$var wire 1 2" fifo_busy $end
$var reg 4 3" fifo_position_r [3:0] $end
$var reg 2 4" fifo_state_r [1:0] $end
$var reg 1 5" i_data_r $end
$var reg 15 6" memory [14:0] $end
$var reg 1 ," o_data_r $end
$var reg 1 7" pop_r $end
$var reg 1 8" reset_r $end
$var reg 1 9" save_r $end
$upscope $end
$upscope $end
$scope begin genblk1[7] $end
$scope module subFIFO $end
$var wire 1 ' clk $end
$var wire 1 :" i_data $end
$var wire 1 ( pop $end
$var wire 1 ! reset $end
$var wire 1 ) save $end
$var wire 1 ;" o_data $end
$var wire 1 <" fifo_s_SAVE $end
$var wire 1 =" fifo_s_POP $end
$var wire 1 >" fifo_s_IDLE $end
$var wire 1 ?" fifo_full $end
$var wire 1 @" fifo_empty $end
$var wire 1 A" fifo_busy $end
$var reg 4 B" fifo_position_r [3:0] $end
$var reg 2 C" fifo_state_r [1:0] $end
$var reg 1 D" i_data_r $end
$var reg 15 E" memory [14:0] $end
$var reg 1 ;" o_data_r $end
$var reg 1 F" pop_r $end
$var reg 1 G" reset_r $end
$var reg 1 H" save_r $end
$upscope $end
$upscope $end
$upscope $end
$upscope $end
$enddefinitions $end
#0
$dumpvars
0H"
0G"
0F"
b0 E"
0D"
b0 C"
b0 B"
0A"
1@"
0?"
1>"
0="
0<"
0;"
0:"
09"
08"
07"
b0 6"
05"
b0 4"
b0 3"
02"
11"
00"
1/"
0."
0-"
0,"
0+"
0*"
0)"
0("
b0 '"
0&"
b0 %"
b0 $"
0#"
1""
0!"
1~
0}
0|
0{
0z
0y
0x
0w
b0 v
0u
b0 t
b0 s
0r
1q
0p
1o
0n
0m
0l
0k
0j
0i
0h
b0 g
0f
b0 e
b0 d
0c
1b
0a
1`
0_
0^
0]
0\
0[
0Z
0Y
b0 X
0W
b0 V
b0 U
0T
1S
0R
1Q
0P
0O
0N
0M
0L
0K
0J
b0 I
0H
b0 G
b0 F
0E
1D
0C
1B
0A
0@
0?
0>
0=
0<
0;
b0 :
09
b0 8
b0 7
06
15
04
13
02
01
00
0/
b0 .
b0 -
b11111111 ,
b0 +
b0 *
0)
0(
0'
b0 &
b0 %
0$
1#
0"
0!
$end
#1
1'
#2
0'
#3
1'
#4
0'
#5
1'
#6
1/
1+"
b1000001 &
b1000001 *
0'
#7
1'
#8
1)
0'
#9
19
1=
1L
1[
1j
1y
1*"
15"
19"
1H"
1'
#10
0/
0+"
b0 &
b0 *
0)
0'
#11
1$
1A"
0>"
1<"
12"
0/"
1-"
1#"
0~
1|
1r
0o
1m
1c
0`
1^
1T
0Q
1O
1E
0B
1@
b11111111 -
16
03
11
b1 C"
0H"
b1 4"
09"
b1 %"
0*"
b1 t
0y
b1 e
0j
b1 V
0[
b1 G
0L
b1 8
0=
1'
#12
0'
#13
0#
01
05
0@
0D
0O
0S
0^
0b
0m
0q
0|
0""
0-"
01"
0<"
b0 ,
0@"
b11 8
b1 :
b1 7
b11 G
b1 F
b11 V
b1 U
b11 e
b1 d
b11 t
b1 s
b11 %"
b1 $"
b11 4"
b1 6"
b1 3"
b11 C"
b1 B"
1'
#14
0'
#15
0$
0A"
1>"
02"
1/"
0#"
1~
0r
1o
0c
1`
0T
1Q
0E
1B
b0 -
06
13
b0 C"
1,"
b0 4"
b0 %"
b0 t
b0 e
b0 V
b0 G
b1000001 %
b1000001 .
10
b0 8
1'
#16
0'
#17
1'
#18
1/
1>
1\
1k
1+"
1)
b1011011 &
b1011011 *
0'
#19
1H"
19"
1*"
1y
1u
1j
1f
1[
1L
1H
1=
1'
#20
0/
0>
0\
0k
0+"
0)
b0 &
b0 *
0'
#21
1$
16
03
11
1E
0B
1@
1T
0Q
1O
1c
0`
1^
1r
0o
1m
1#"
0~
1|
12"
0/"
1-"
b11111111 -
1A"
0>"
1<"
0=
b1 8
0L
b1 G
0[
b1 V
0j
b1 e
0y
b1 t
0*"
b1 %"
09"
b1 4"
0H"
b1 C"
1'
#22
0'
#23
0<"
0-"
0|
0m
0^
0O
0@
01
b10 B"
b11 C"
b10 3"
b11 6"
b11 4"
b10 $"
b11 %"
b10 s
b10 v
b11 t
b10 d
b10 g
b11 e
b10 U
b11 V
b10 F
b10 I
b11 G
b10 7
b11 :
b11 8
1'
#24
0'
#25
0$
06
13
0E
1B
0T
1Q
0c
1`
0r
1o
0#"
1~
02"
1/"
b0 -
0A"
1>"
b0 8
b0 G
b0 V
b0 e
b0 t
b0 %"
b0 4"
b0 C"
1'
#26
0'
#27
1'
#28
1/
1>
1z
1+"
1)
b1100011 &
b1100011 *
0'
#29
1=
1L
1[
0f
1j
0u
1y
1&"
1*"
19"
1H"
1'
#30
0/
0>
0z
0+"
0)
b0 &
b0 *
0'
#31
1$
1A"
0>"
1<"
12"
0/"
1-"
1#"
0~
1|
1r
0o
1m
1c
0`
1^
1T
0Q
1O
1E
0B
1@
b11111111 -
16
03
11
b1 C"
0H"
b1 4"
09"
b1 %"
0*"
b1 t
0y
b1 e
0j
b1 V
0[
b1 G
0L
b1 8
0=
1'
#32
0'
#33
01
0@
0O
0^
0m
0|
0-"
0<"
b11 8
b111 :
b11 7
b11 G
b110 I
b11 F
b11 V
b11 U
b11 e
b11 d
b11 t
b11 s
b11 %"
b100 '"
b11 $"
b11 4"
b111 6"
b11 3"
b11 C"
b11 B"
1'
#34
0'
#35
0$
0A"
1>"
02"
1/"
0#"
1~
0r
1o
0c
1`
0T
1Q
0E
1B
b0 -
06
13
b0 C"
b0 4"
b0 %"
b0 t
b0 e
b0 V
b0 G
b0 8
1'
#36
0'
#37
1'
#38
1(
0'
#39
1F"
17"
1("
1w
1h
1Y
1J
1;
1'
#40
0(
0'
#41
1$
16
03
12
1E
0B
1A
1T
0Q
1P
1c
0`
1_
1r
0o
1n
1#"
0~
1}
12"
0/"
1."
b11111111 -
1A"
0>"
1="
0;
b10 8
0J
b10 G
0Y
b10 V
0h
b10 e
0w
b10 t
0("
b10 %"
07"
b10 4"
0F"
b10 C"
1'
#42
0'
#43
0="
0."
0}
0n
0_
0P
0A
02
b10 B"
b11 C"
b10 3"
b11 6"
b11 4"
b10 $"
b10 '"
b11 %"
b10 s
b1 v
b11 t
b10 d
b1 g
b11 e
b10 U
b11 V
b10 F
b11 I
b11 G
b10 7
b11 :
b11 8
1'
#44
0'
#45
0$
06
13
0E
1B
0T
1Q
0c
1`
0r
1o
0#"
1~
02"
1/"
b0 -
0A"
1>"
b0 8
b0 G
1?
b0 V
b0 e
1]
b0 t
b1011011 %
b1011011 .
1l
b0 %"
b0 4"
b0 C"
1'
#46
0'
#47
1'
#48
1(
0'
#49
1;
1J
1Y
1h
1w
1("
17"
1F"
1'
#50
0(
0'
#51
1$
1A"
0>"
1="
12"
0/"
1."
1#"
0~
1}
1r
0o
1n
1c
0`
1_
1T
0Q
1P
1E
0B
1A
b11111111 -
16
03
12
b10 C"
0F"
b10 4"
07"
b10 %"
0("
b10 t
0w
b10 e
0h
b10 V
0Y
b10 G
0J
b10 8
0;
1'
#52
0'
#53
02
0A
0P
0_
0n
0}
0."
0="
b11 8
b1 :
b1 7
b11 G
b1 I
b1 F
b11 V
b1 U
b11 e
b0 g
b1 d
b11 t
b0 v
b1 s
b11 %"
b1 '"
b1 $"
b11 4"
b1 6"
b1 3"
b11 C"
b1 B"
1'
#54
0'
#55
0$
0A"
1>"
02"
1/"
0#"
1~
0r
1o
0c
1`
0T
1Q
0E
1B
b0 -
06
13
b0 C"
b0 4"
1{
b0 %"
0l
b0 t
b1100011 %
b1100011 .
0]
b0 e
b0 V
b0 G
b0 8
1'
#56
0'
#57
1'
#58
1(
0'
#59
1F"
17"
1("
1w
1h
1Y
1J
1;
1'
#60
0(
0'
#61
1$
16
03
12
1E
0B
1A
1T
0Q
1P
1c
0`
1_
1r
0o
1n
1#"
0~
1}
12"
0/"
1."
b11111111 -
1A"
0>"
1="
0;
b10 8
0J
b10 G
0Y
b10 V
0h
b10 e
0w
b10 t
0("
b10 %"
07"
b10 4"
0F"
b10 C"
1'
#62
0'
#63
1#
1@"
0="
11"
0."
1""
0}
1q
0n
1b
0_
1S
0P
1D
0A
b11111111 ,
15
02
b0 B"
b11 C"
b0 3"
b0 6"
b11 4"
b0 $"
b0 '"
b11 %"
b0 s
b11 t
b0 d
b11 e
b0 U
b11 V
b0 F
b0 I
b11 G
b0 7
b0 :
b11 8
1'
#64
0'
#65
0$
06
13
0E
1B
0T
1Q
0c
1`
0r
1o
0#"
1~
02"
1/"
b0 -
0A"
1>"
b0 8
00
b0 G
0?
b0 V
b0 e
b0 t
b0 %"
0{
b0 4"
b0 %
b0 .
0,"
b0 C"
1'
