ICEstick/USB3300_parser_V1/modules/fifo_stack_u.v
/*
 * MIT License
 *
 * Copyright (c) 2018 Mario Rubio
 *
 * Permission is hereby granted, free of charge, to any person obtaining a copy
 * of this software and associated documentation files (the 'Software'), to deal
 * in the Software without restriction, including without limitation the rights
 * to use, copy, modify, merge, publish, distribute, sublicense, and/or sell
 * copies of the Software, and to permit persons to whom the Software is
 * furnished to do so, subject to the following conditions:
 *
 * The above copyright notice and this permission notice shall be included in all
 * copies or substantial portions of the Software.
 *
 * THE SOFTWARE IS PROVIDED 'AS IS', WITHOUT WARRANTY OF ANY KIND, EXPRESS OR
 * IMPLIED, INCLUDING BUT NOT LIMITED TO THE WARRANTIES OF MERCHANTABILITY,
 * FITNESS FOR A PARTICULAR PURPOSE AND NONINFRINGEMENT. IN NO EVENT SHALL THE
 * AUTHORS OR COPYRIGHT HOLDERS BE LIABLE FOR ANY CLAIM, DAMAGES OR OTHER
 * LIABILITY, WHETHER IN AN ACTION OF CONTRACT, TORT OR OTHERWISE, ARISING FROM,
 * OUT OF OR IN CONNECTION WITH THE SOFTWARE OR THE USE OR OTHER DEALINGS IN THE
 * SOFTWARE.
 */

/*
 * Revision History:
 *     Initial: 2018/05/22      Mario Rubio
 */

module fifo_stack_u #(parameter STACK_SIZE = 8)
                     (input  wire clk,       // Reference clock
                      input  wire i_data,    // New input data
                      input  wire save,      // Input to save the current bit in i_data
                      input  wire pop,       // Input to pop the first bit in the stack
                      input  wire reset,     // Input to reset the stack
                      output wire o_data,    // Output bit, always the first bit in the stack
                      output wire fifo_full, // Stack full flag
                      output wire fifo_empty,// Stack empty flag
                      output wire fifo_busy  // Module Busy, no new operation allowed
                      );

    localparam STACK_SIZE_N = $clog2(STACK_SIZE+1)/$clog2(2);

    /// FIFO regs and wires
    // Outputs
    reg o_data_r = 1'b0; assign o_data = o_data_r;

    // Inputs
    reg i_data_r = 1'b0;
    reg save_r   = 1'b0;
    reg pop_r    = 1'b0;
    reg reset_r  = 1'b0;
    always @(posedge clk) begin
        if(fifo_s_IDLE && save == 1'b1) begin
            i_data_r <= i_data;
        end
    end
    always @(posedge clk) begin
        save_r   <= save;
        pop_r    <= pop;
        reset_r  <= reset;
    end

    // Buffers
    reg [STACK_SIZE-1:0]memory = {STACK_SIZE{1'b0}};

    // Control registers
    reg [STACK_SIZE_N-1:0]fifo_position_r = {STACK_SIZE_N{1'b0}};
    reg [1:0]fifo_state_r = 2'b0;

    // Flags
    wire fifo_s_IDLE;
    wire fifo_s_SAVE;
    wire fifo_s_POP;
    wire fifo_s_RST;

    // Assigns
    assign fifo_s_IDLE = (fifo_state_r == FIFO_IDLE) ? 1'b1 : 1'b0;
    assign fifo_s_SAVE = (fifo_state_r == FIFO_SAVE) ? 1'b1 : 1'b0;
    assign fifo_s_POP  = (fifo_state_r == FIFO_POP)  ? 1'b1 : 1'b0;
    assign fifo_full   = (fifo_position_r == (STACK_SIZE+1)) ? 1'b1 : 1'b0;
    assign fifo_empty  = (fifo_position_r == 0) ? 1'b1 : 1'b0;
    assign fifo_busy   = !fifo_s_IDLE;

    /// End of FIFO regs and wires

    /// FIFO states
    localparam FIFO_IDLE = 2'b00; // Default state. Do nothing.
    localparam FIFO_SAVE = 2'b01; // Save a new value into the memory
    localparam FIFO_POP  = 2'b10; // Pop the first value of the memory
    localparam FIFO_WAIT = 2'b11; // Delay to show the new values in the output
    /// End of FIFO states

    /// FIFO controller
    always @(posedge clk) begin
        if(reset_r) begin
            fifo_state_r <= FIFO_IDLE;
            memory <= {STACK_SIZE{1'b0}};
            fifo_position_r <= {STACK_SIZE_N{1'b0}};
        end
        else begin
            case(fifo_state_r)
                FIFO_IDLE: begin
                    if(save_r && !pop_r)
                        fifo_state_r <= FIFO_SAVE;
                    else if(pop_r && !save_r)
                        fifo_state_r <= FIFO_POP;
                    else
                        fifo_state_r <= FIFO_IDLE;
                end
                FIFO_SAVE: begin
                    fifo_state_r <= FIFO_WAIT;
                end
                FIFO_POP: begin
                    fifo_state_r <= FIFO_WAIT;
                end
                FIFO_WAIT: begin
                    fifo_state_r <= FIFO_IDLE;
                end
                default: begin
                    fifo_state_r <= FIFO_IDLE;
                end
            endcase
        end
    end

    always @(posedge clk) begin
        o_data_r <= memory[0];
    end

    // Memory modify
    always @(posedge clk) begin
        if(fifo_s_IDLE == 1'b1) begin
        end
        else if(fifo_s_SAVE == 1'b1) begin
            if(fifo_full == 1'b0) begin
                memory[fifo_position_r] <= i_data_r;
            end
        end
        else if(fifo_s_POP == 1'b1) begin
            if(fifo_empty == 1'b0) begin
                memory <= memory>>1;
            end
        end
    end

    // fifo position change
    always @(posedge clk) begin
        if(fifo_s_IDLE == 1'b1) begin
        end
        else if(fifo_s_SAVE == 1'b1) begin
            if(fifo_full == 1'b0) begin
                fifo_position_r <= fifo_position_r + 1'b1;
            end
        end
        else if(fifo_s_POP == 1'b1) begin
            if(fifo_empty == 1'b0) begin
                fifo_position_r <= fifo_position_r - 1'b1;
            end
        end
    end
    /// End of FIFO controller

endmodule

ICEstick/USB3300_parser_V1/modules/fifo_stack_u_tb.v
/*
 * MIT License
 *
 * Copyright (c) 2018 Mario Rubio
 *
 * Permission is hereby granted, free of charge, to any person obtaining a copy
 * of this software and associated documentation files (the 'Software'), to deal
 * in the Software without restriction, including without limitation the rights
 * to use, copy, modify, merge, publish, distribute, sublicense, and/or sell
 * copies of the Software, and to permit persons to whom the Software is
 * furnished to do so, subject to the following conditions:
 *
 * The above copyright notice and this permission notice shall be included in all
 * copies or substantial portions of the Software.
 *
 * THE SOFTWARE IS PROVIDED 'AS IS', WITHOUT WARRANTY OF ANY KIND, EXPRESS OR
 * IMPLIED, INCLUDING BUT NOT LIMITED TO THE WARRANTIES OF MERCHANTABILITY,
 * FITNESS FOR A PARTICULAR PURPOSE AND NONINFRINGEMENT. IN NO EVENT SHALL THE
 * AUTHORS OR COPYRIGHT HOLDERS BE LIABLE FOR ANY CLAIM, DAMAGES OR OTHER
 * LIABILITY, WHETHER IN AN ACTION OF CONTRACT, TORT OR OTHERWISE, ARISING FROM,
 * OUT OF OR IN CONNECTION WITH THE SOFTWARE OR THE USE OR OTHER DEALINGS IN THE
 * SOFTWARE.
 */

/*
 * Revision History:
 *     Initial: 2018/05/22      Mario Rubio
 */

module fifo_stack_u_tb();

    reg clk = 1'b0;
    reg I_DATA = 1'b0;
    reg save = 1'b0;
    reg pop = 1'b0;
    wire reset; assign reset = 1'b0;
    wire O_DATA;
    wire full;
    wire empty;
    wire busy;
    fifo_stack_u FIFO_u(clk, I_DATA, save, pop, reset, 
                O_DATA, full, empty, busy);

    // reg [2:0]init_state = 3'b0;
    // wire stt1; assign stt1 = (init_state == 3'b000) ? 1'b1: 1'b0;
    // wire stt2; assign stt2 = (init_state == 3'b001) ? 1'b1: 1'b0;
    // wire stt3; assign stt3 = (init_state == 3'b010) ? 1'b1: 1'b0;
    // wire stt4; assign stt4 = (init_state == 3'b011) ? 1'b1: 1'b0;
    // wire stt5; assign stt5 = (init_state == 3'b100) ? 1'b1: 1'b0;
    // wire stt6; assign stt6 = (init_state == 3'b101) ? 1'b1: 1'b0;
    // wire stt7; assign stt7 = (init_state == 3'b110) ? 1'b1: 1'b0;
    // wire stt8; assign stt8 = (init_state == 3'b111) ? 1'b1: 1'b0;
    // always @(posedge clk) begin
    //     case(init_state)
    //         3'b000: begin
    //             if(!busy)
    //                 init_state <= 3'b001;
    //             else
    //                 init_state <= 3'b000;
    //         end
    //         3'b001: begin
    //             if(!busy)
    //                 init_state <= 3'b010;
    //             else
    //                 init_state <= 3'b001;
    //         end
    //         3'b010: begin
    //             if(!busy)
    //                 init_state <= 3'b011;
    //             else
    //                 init_state <= 3'b010;
    //         end
    //         3'b011: begin
    //             if(!busy)
    //                 init_state <= 3'b100;
    //             else
    //                 init_state <= 3'b011;
    //         end
    //         3'b100: begin
    //             if(!busy)
    //                 init_state <= 3'b101;
    //             else
    //                 init_state <= 3'b100;
    //         end
    //         3'b101: begin
    //             if(!busy)
    //                 init_state <= 3'b110;
    //             else
    //                 init_state <= 3'b101;
    //         end
    //         3'b110: begin
    //             if(!busy)
    //                 init_state <= 3'b111;
    //             else
    //                 init_state <= 3'b110;
    //         end
    //         3'b111: begin
    //             if(!busy)
    //                 init_state <= 3'b000;
    //             else
    //                 init_state <= 3'b111;
    //         end
    //         default:
    //             init_state <= 3'b000;
    //     endcase
    // end
    // always @(posedge clk) begin
    //     if(stt1 == 1'b1 && !busy) begin
    //         I_DATA <= 1'b1;
    //         save <= 1'b1; 
    //         pop <= 1'b0;
    //     end
    //     if(stt2 == 1'b1 && !busy) begin
    //         I_DATA <= 1'b0;
    //         save <= 1'b1; 
    //         pop <= 1'b0;
    //     end
    //     if(stt3 == 1'b1 && !busy) begin
    //         I_DATA <= 1'b0;
    //         save <= 1'b1; 
    //         pop <= 1'b0;
    //     end
    //     if(stt4 == 1'b1 && !busy) begin
    //         I_DATA <= 1'b1;
    //         save <= 1'b1; 
    //         pop <= 1'b0;
    //     end
    //     if(stt5 == 1'b1 && !busy) begin
    //         pop <= 1'b1;
    //         save <= 1'b0; 
    //     end
    //     if(stt6 == 1'b1 && !busy) begin
    //         pop <= 1'b1;
    //         save <= 1'b0; 
    //     end
    //     if(stt7 == 1'b1 && !busy) begin
    //         pop <= 1'b1; 
    //         save <= 1'b0; 
    //     end
    //     if(stt8 == 1'b1 && !busy) begin
    //         pop <= 1'b1; 
    //         save <= 1'b0; 
    //     end
    // end

    // Clock
    always #1 clk = ~clk;

    initial begin
        $dumpfile("fifo_stack_u.vcd");
        $dumpvars(0, fifo_stack_u_tb);

        // $monitor("Input: %1b  Output: %1b  Save: %1b  Pop: %1b  Full: %1b  Empty: %1b", I_DATA, O_DATA, save, pop, full, empty);
        
        $display(" IN   SAVE   OUT  EMPT ");
        $display("Save 1 [1]");
        #2 
        #2 save <= 0; pop <= 0;

           $display("I: %b. S: %b. O: %b. E: %b. [%b]", I_DATA, save, O_DATA, empty, busy);
        #2 I_DATA <= 1;

           $display("I: %b. S: %b. O: %b. E: %b. [%b]", I_DATA, save, O_DATA, empty, busy);
        #2 save <= 1;

        #2 $display("I: %b. S: %b. O: %b. E: %b. [%b]", I_DATA, save, O_DATA, empty, busy);
           save <= 0; I_DATA <= 0;

        #2 $display("I: %b. S: %b. O: %b. E: %b. [%b]", I_DATA, save, O_DATA, empty, busy);
        #2 $display("I: %b. S: %b. O: %b. E: %b. [%b]", I_DATA, save, O_DATA, empty, busy);
        #2 $display("I: %b. S: %b. O: %b. E: %b. [%b]", I_DATA, save, O_DATA, empty, busy);
        
           $display("Save 2 [0]");
        #2 I_DATA <= 0; save <= 1;
        
           $display("I: %b. S: %b. O: %b. E: %b. [%b]", I_DATA, save, O_DATA, empty, busy);
        #2 I_DATA <= 0; save <= 0;
           $display("I: %b. S: %b. O: %b. E: %b. [%b]", I_DATA, save, O_DATA, empty, busy);

        #2 $display("I: %b. S: %b. O: %b. E: %b. [%b]", I_DATA, save, O_DATA, empty, busy);
        #2 $display("I: %b. S: %b. O: %b. E: %b. [%b]", I_DATA, save, O_DATA, empty, busy);
        #2 $display("I: %b. S: %b. O: %b. E: %b. [%b]", I_DATA, save, O_DATA, empty, busy);
        
           $display("Save 3 [1]");
        #2 I_DATA <= 1; save <= 1;
        
           $display("I: %b. S: %b. O: %b. E: %b. [%b]", I_DATA, save, O_DATA, empty, busy);
        #2 I_DATA <= 0; save <= 0;
           $display("I: %b. S: %b. O: %b. E: %b. [%b]", I_DATA, save, O_DATA, empty, busy);

        #2 $display("I: %b. S: %b. O: %b. E: %b. [%b]", I_DATA, save, O_DATA, empty, busy);
        #2 $display("I: %b. S: %b. O: %b. E: %b. [%b]", I_DATA, save, O_DATA, empty, busy);
        #2 $display("I: %b. S: %b. O: %b. E: %b. [%b]", I_DATA, save, O_DATA, empty, busy);

           $display("Pop 1");
        #2 pop <=1;
        
           $display("I: %b. S: %b. O: %b. E: %b. [%b]", I_DATA, save, O_DATA, empty, busy);
        #2 pop <= 0;

        #2 $display("I: %b. S: %b. O: %b. E: %b. [%b]", I_DATA, save, O_DATA, empty, busy);
        #2 $display("I: %b. S: %b. O: %b. E: %b. [%b]", I_DATA, save, O_DATA, empty, busy);
        #2 $display("I: %b. S: %b. O: %b. E: %b. [%b]", I_DATA, save, O_DATA, empty, busy);
        
           $display("Pop 2");
        #2 pop <=1;
        
           $display("I: %b. S: %b. O: %b. E: %b. [%b]", I_DATA, save, O_DATA, empty, busy);
        #2 pop <= 0;

        #2 $display("I: %b. S: %b. O: %b. E: %b. [%b]", I_DATA, save, O_DATA, empty, busy);
        #2 $display("I: %b. S: %b. O: %b. E: %b. [%b]", I_DATA, save, O_DATA, empty, busy);
        #2 $display("I: %b. S: %b. O: %b. E: %b. [%b]", I_DATA, save, O_DATA, empty, busy);
        
           $display("Pop 3");
        #2 pop <=1;
        
           $display("I: %b. S: %b. O: %b. E: %b. [%b]", I_DATA, save, O_DATA, empty, busy);
        #2 pop <= 0;

        #2 $display("I: %b. S: %b. O: %b. E: %b. [%b]", I_DATA, save, O_DATA, empty, busy);
        #2 $display("I: %b. S: %b. O: %b. E: %b. [%b]", I_DATA, save, O_DATA, empty, busy);
        #2 $display("I: %b. S: %b. O: %b. E: %b. [%b]", I_DATA, save, O_DATA, empty, busy);

        #64 $finish;
    end

endmodule

ICEstick/USB3300_parser_V1/modules/fifo_stack_u.vcd
$date
	Wed May 23 18:49:05 2018
$end
$version
	Icarus Verilog
$end
$timescale
	1s
$end
$scope module fifo_stack_u_tb $end
$var wire 1 ! reset $end
$var wire 1 " full $end
$var wire 1 # empty $end
$var wire 1 $ busy $end
$var wire 1 % O_DATA $end
$var reg 1 & I_DATA $end
$var reg 1 ' clk $end
$var reg 1 ( pop $end
$var reg 1 ) save $end
$scope module FIFO_u $end
$var wire 1 ' clk $end
$var wire 1 & i_data $end
$var wire 1 % o_data $end
$var wire 1 ( pop $end
$var wire 1 ! reset $end
$var wire 1 ) save $end
$var wire 1 * fifo_s_SAVE $end
$var wire 1 + fifo_s_POP $end
$var wire 1 , fifo_s_IDLE $end
$var wire 1 " fifo_full $end
$var wire 1 # fifo_empty $end
$var wire 1 $ fifo_busy $end
$var reg 4 - fifo_position_r [3:0] $end
$var reg 2 . fifo_state_r [1:0] $end
$var reg 1 / i_data_r $end
$var reg 8 0 memory [7:0] $end
$var reg 1 1 o_data_r $end
$var reg 1 2 pop_r $end
$var reg 1 3 reset_r $end
$var reg 1 4 save_r $end
$upscope $end
$upscope $end
$enddefinitions $end
#0
$dumpvars
04
03
02
01
b0 0
0/
b0 .
b0 -
1,
0+
0*
0)
0(
0'
0&
0%
0$
1#
0"
0!
$end
#1
1'
#2
0'
#3
1'
#4
0'
#5
1'
#6
1&
0'
#7
1'
#8
1)
0'
#9
1/
14
1'
#10
0&
0)
0'
#11
1$
0,
1*
b1 .
04
1'
#12
0'
#13
0*
0#
b11 .
b1 0
b1 -
1'
#14
0'
#15
0$
1,
1%
11
b0 .
1'
#16
0'
#17
1'
#18
1)
0'
#19
14
0/
1'
#20
0)
0'
#21
1$
0,
1*
04
b1 .
1'
#22
0'
#23
0*
b10 -
b11 .
1'
#24
0'
#25
0$
1,
b0 .
1'
#26
0'
#27
1'
#28
1)
1&
0'
#29
1/
14
1'
#30
0)
0&
0'
#31
1$
0,
1*
b1 .
04
1'
#32
0'
#33
0*
b11 .
b101 0
b11 -
1'
#34
0'
#35
0$
1,
b0 .
1'
#36
0'
#37
1'
#38
1(
0'
#39
12
1'
#40
0(
0'
#41
1$
0,
1+
02
b10 .
1'
#42
0'
#43
0+
b10 -
b10 0
b11 .
1'
#44
0'
#45
0$
1,
b0 .
0%
01
1'
#46
0'
#47
1'
#48
1(
0'
#49
12
1'
#50
0(
0'
#51
1$
0,
1+
b10 .
02
1'
#52
0'
#53
0+
b11 .
b1 0
b1 -
1'
#54
0'
#55
0$
1,
1%
11
b0 .
1'
#56
0'
#57
1'
#58
1(
0'
#59
12
1'
#60
0(
0'
#61
1$
0,
1+
02
b10 .
1'
#62
0'
#63
1#
0+
b0 -
b0 0
b11 .
1'
#64
0'
#65
0$
1,
b0 .
0%
01
1'
